ulldConfig/Config.py
ulldConfig/__init__.py
UlldConfig-0.1.1.dist-info/METADATA
UlldConfig-0.1.1.dist-info/WHEEL
UlldConfig-0.1.1.dist-info/top_level.txt
UlldConfig-0.1.1.dist-info/RECORD
